README.rst
setup.py
nodewire/__init__.py
nodewire/client.py
nodewire/client2.py
nodewire/db.py
nodewire/ddb.py
nodewire/message.py
nodewire/node.py
nodewire/nodewire.py
nodewire.egg-info/PKG-INFO
nodewire.egg-info/SOURCES.txt
nodewire.egg-info/dependency_links.txt
nodewire.egg-info/not-zip-safe
nodewire.egg-info/requires.txt
nodewire.egg-info/top_level.txt