Metadata-Version: 1.0
Name: nodewire
Version: 2.0.1
Summary: Nodewire
Home-page: http://www.nodewire.org
Author: Ahmad Sadiq
Author-email: sadiq.a.ahmad@gmail.com
License: BSD
Platform: UNKNOWN
